pytcspc/__init__.py
pytcspc/batch.py
pytcspc/fcs.py
pytcspc/flim.py
pytcspc/multipletau.py
pytcspc/presets.py
pytcspc/sdt.py
pytcspc/sdtfile.py
pytcspc/spc.py
pytcspc/util.py
pytcspc-0.2.5.dist-info/METADATA
pytcspc-0.2.5.dist-info/WHEEL
pytcspc-0.2.5.dist-info/licenses/LICENSE.md
pytcspc-0.2.5.dist-info/RECORD
