Metadata-Version: 2.4
Name: pytcspc
Version: 0.2.5
Summary: Time-correlated single photon counting (TCSPC) data analysis
Project-URL: Homepage, https://github.com/easunarunachalam/pyTCSPC
Author-email: Easun Arunachalam <arunachalam@g.harvard.edu>
License: MIT License
License-File: LICENSE.md
Keywords: example,setuptools
Classifier: License :: OSI Approved :: MIT License
Classifier: Programming Language :: Python :: 3
Requires-Dist: bottleneck>=1.4.2
Requires-Dist: corner>=2.2.2
Requires-Dist: dask
Requires-Dist: h5py
Requires-Dist: joblib
Requires-Dist: matplotlib
Requires-Dist: multipletau>=0.4.1
Requires-Dist: numexpr>=2.8.4
Requires-Dist: numpy<2
Requires-Dist: pandas
Requires-Dist: scikit-image
Requires-Dist: scipy
Requires-Dist: sdtfile>=2024.5.24
Requires-Dist: tqdm
Requires-Dist: xarray
Requires-Dist: zarr
